slipo/__init__.py
slipo/__version__.py
slipo/catalog.py
slipo/client.py
slipo/exceptions.py
slipo/filesystem.py
slipo/operation.py
slipo/process.py
slipo/types.py
slipo/utils.py
slipo-0.1.6.dist-info/LICENSE
slipo-0.1.6.dist-info/METADATA
slipo-0.1.6.dist-info/WHEEL
slipo-0.1.6.dist-info/top_level.txt
slipo-0.1.6.dist-info/RECORD
