Metadata-Version: 2.1
Name: slipo
Version: 0.1.6
Summary: SLIPO API Python client
Home-page: https://github.com/SLIPO-EU/slipo-python
Author: Yannis Kouvaras
Author-email: jkouvar@imis.athena-innovation.gr
License: Apache Software License
Keywords: poi linked-data point-of-interest data-integration
Platform: UNKNOWN
Classifier: Programming Language :: Python :: 3
Classifier: Intended Audience :: Developers
Classifier: License :: OSI Approved :: Apache Software License
Classifier: Operating System :: OS Independent
Requires-Python: >=3
Requires-Dist: requests (>=2.21.0)
